.gitignore
CODE_OF_CONDUCT.md
LICENSE
MANIFEST.in
README.md
_config.yml
setup.py
doc/Doxyfile
doc/index.dox
doc/recpermissions.png
doc/recpermissions.svg
doc/rocker.png
doc/ttyrec/howto.py
doc/ttyrec/recpermissions_howto_en
doc/ttyrec/recpermissions_howto_en.gif
doc/ttyrec/recpermissions_howto_es
doc/ttyrec/recpermissions_howto_es.gif
locale/es.po
locale/fr.po
locale/recpermissions.pot
man/es/man1/recpermissions.1
man/fr/man1/recpermissions.1
man/man1/recpermissions.1
recpermissions/__init__.py
recpermissions/core.py
recpermissions/version.py
recpermissions.egg-info/PKG-INFO
recpermissions.egg-info/SOURCES.txt
recpermissions.egg-info/dependency_links.txt
recpermissions.egg-info/entry_points.txt
recpermissions.egg-info/not-zip-safe
recpermissions.egg-info/requires.txt
recpermissions.egg-info/top_level.txt
recpermissions/locale/es/LC_MESSAGES/recpermissions.mo
recpermissions/locale/fr/LC_MESSAGES/recpermissions.mo