Metadata-Version: 2.1
Name: recpermissions
Version: 1.10.0
Summary: Change files and directories permisions and owner recursivily from current directory
Home-page: https://github.com/Turulomio/recpermissions
Author: Turulomio
Author-email: turulomio@yahoo.es
License: GPL-3
Keywords: change permissions ownner files directories
Platform: UNKNOWN
Classifier: Development Status :: 4 - Beta
Classifier: Intended Audience :: System Administrators
Classifier: Topic :: System :: Systems Administration
Classifier: License :: OSI Approved :: GNU General Public License v3 (GPLv3)
Classifier: Programming Language :: Python :: 3
